instanexus/__init__.py
instanexus/__main__.py
instanexus/alignment.py
instanexus/assembly.py
instanexus/clustering.py
instanexus/consensus.py
instanexus/helpers.py
instanexus/main.py
instanexus/preprocessing.py
instanexus/visualization.py
instanexus-0.2.0.dist-info/METADATA
instanexus-0.2.0.dist-info/WHEEL
instanexus-0.2.0.dist-info/entry_points.txt
instanexus-0.2.0.dist-info/licenses/LICENSE
instanexus-0.2.0.dist-info/RECORD
