Metadata-Version: 2.4
Name: instanexus
Version: 0.2.0
Summary: End-to-end workflow for de novo protein sequencing based on InstaNovo
Project-URL: Homepage, https://github.com/Multiomics-Analytics-Group/InstaNexus
Project-URL: Issues, https://github.com/Multiomics-Analytics-Group/InstaNexus/issues
License: MIT
License-File: LICENSE
Requires-Python: >=3.10
